scooze/__init__.py
scooze/api/README.md
scooze/api/__init__.py
scooze/api/bulkdata.py
scooze/api/card.py
scooze/api/deck.py
scooze/api/utils.py
scooze/bulkdata.py
scooze/card.py
scooze/cardlist.py
scooze/cardparts.py
scooze/catalogs.py
scooze/config.py
scooze/configs/logging_config.json
scooze/console/__init__.py
scooze/console/cli.py
scooze/console/commands/delete.py
scooze/console/commands/load/cards.py
scooze/console/commands/load/decks.py
scooze/console/commands/run.py
scooze/console/commands/save/cards.py
scooze/deck.py
scooze/enums.py
scooze/errors.py
scooze/logger.py
scooze/main.py
scooze/models/__init__.py
scooze/models/card.py
scooze/models/cardparts.py
scooze/models/deck.py
scooze/models/utils.py
scooze/mongo.py
scooze/routers/__init__.py
scooze/routers/card.py
scooze/routers/cards.py
scooze/routers/deck.py
scooze/routers/decks.py
scooze/static/index.html
scooze/utils.py
scooze-2.0.2.dist-info/LICENSE
scooze-2.0.2.dist-info/METADATA
scooze-2.0.2.dist-info/WHEEL
scooze-2.0.2.dist-info/entry_points.txt
scooze-2.0.2.dist-info/RECORD
