Metadata-Version: 2.3
Name: scooze
Version: 2.0.2
Summary: A flexible data layer for applications working with Magic: the Gathering cards and decks.
Author: Alexander Gimmi
Author-email: iambroadband@gmail.com
Requires-Python: >=3.11,<4
Classifier: Programming Language :: Python :: 3
Classifier: Programming Language :: Python :: 3.11
Classifier: Programming Language :: Python :: 3.12
Classifier: Programming Language :: Python :: 3.13
Requires-Dist: beanie (>=1.23.0,<2.0.0)
Requires-Dist: cleo (>=2.0.1,<3.0.0)
Requires-Dist: fastapi (>=0.100.0,<1.0.0)
Requires-Dist: frozendict (>=2.3.8,<3.0.0)
Requires-Dist: ijson (>=3.2.3,<4.0.0)
Requires-Dist: motor (>=3.2.0,<4.0.0)
Requires-Dist: pydantic (>=2.0.0)
Requires-Dist: pydantic-settings (>=2.0.0,<3.0.0)
Requires-Dist: requests (>=2.32.2,<3.0.0)
Requires-Dist: setuptools (>=72.0.0,<73.0.0)
Requires-Dist: uvicorn[standard] (>=0.23.1,<0.24.0)
Requires-Dist: venv-run (>=0.2.0,<0.3.0)
Project-URL: documentation, https://scooze.readthedocs.io
Project-URL: homepage, https://github.com/arcavios/scooze
Project-URL: repository, https://github.com/arcavios/scooze
